drsession.py
setup.py
drsession.egg-info/PKG-INFO
drsession.egg-info/SOURCES.txt
drsession.egg-info/dependency_links.txt
drsession.egg-info/requires.txt
drsession.egg-info/top_level.txt