Metadata-Version: 1.0
Name: drsession
Version: 1.2.0
Summary: Derek's Redis Session Middleware
Home-page: https://github.com/keredson/drsession
Author: Derek Anderson
Author-email: public@kered.org
License: UNKNOWN
Platform: UNKNOWN
